<?xml version="1.0" encoding="utf-8"?>
<!-- Copyright NuoBiT - Kilian Niubo <kniubo@nuobit.com>
     License AGPL-3.0 or later (http://www.gnu.org/licenses/agpl) -->
<odoo>
    <record id="product_category_form_view" model="ir.ui.view">
        <field name="model">product.category</field>
        <field name="inherit_id" ref="product.product_category_form_view"/>
        <field name="arch" type="xml">
            <group name="first" position="after">
                <group col="2">
                    <field name="investment_capital_asset" options="{'no_create': True, 'no_open': True}"
                           class="oe_inline"/>
                </group>
            </group>
        </field>
    </record>
    <record id="product_category_list_view" model="ir.ui.view">
        <field name="model">product.category</field>
        <field name="inherit_id" ref="product.product_category_list_view"/>
        <field name="arch" type="xml">
            <xpath expr="//tree" position="inside">
                <field name="investment_capital_asset"/>
            </xpath>
        </field>
    </record>
</odoo>
