<?xml version="1.0" encoding="utf-8" ?>
<!-- Copyright NuoBiT - Frank Cespedes <eantones@nuobit.com>
     License AGPL-3.0 or later (http://www.gnu.org/licenses/agpl) -->
<odoo>
    <record id="contract_contract_form_view" model="ir.ui.view">
        <field name="name">contract.contract.inherit</field>
        <field name="model">contract.contract</field>
        <field
            name="inherit_id"
            ref="contract_payment_mode.contract_contract_form_view"
        />
        <field name="arch" type="xml">
            <field name="payment_mode_id" position="attributes">
                <attribute name="readonly">True</attribute>
                <attribute name="force_save">True</attribute>
            </field>
        </field>
    </record>
</odoo>
